icclim/.gitignore
icclim/__init__.py
icclim/exception.py
icclim/frequency.py
icclim/logger.py
icclim/main.py
icclim/rechunk.py
icclim/_core/__init__.py
icclim/_core/climate_variable.py
icclim/_core/constants.py
icclim/_core/input_parsing.py
icclim/_core/utils.py
icclim/_core/generic/__init__.py
icclim/_core/generic/functions.py
icclim/_core/generic/generic_templates.py
icclim/_core/generic/indicator.py
icclim/_core/generic/threshold/__init__.py
icclim/_core/generic/threshold/basic.py
icclim/_core/generic/threshold/bounded.py
icclim/_core/generic/threshold/percentile.py
icclim/_core/generic/threshold/threshold_templates.py
icclim/_core/legacy/__init__.py
icclim/_core/legacy/user_index/__init__.py
icclim/_core/legacy/user_index/calc_operation.py
icclim/_core/legacy/user_index/model.py
icclim/_core/legacy/user_index/parse.py
icclim/_core/model/__init__.py
icclim/_core/model/cf_calendar.py
icclim/_core/model/global_metadata.py
icclim/_core/model/icclim_types.py
icclim/_core/model/in_file_dictionary.py
icclim/_core/model/index_config.py
icclim/_core/model/index_group.py
icclim/_core/model/indicator.py
icclim/_core/model/logical_link.py
icclim/_core/model/netcdf_version.py
icclim/_core/model/operator.py
icclim/_core/model/quantile_interpolation.py
icclim/_core/model/registry.py
icclim/_core/model/standard_index.py
icclim/_core/model/standard_variable.py
icclim/_core/model/threshold.py
icclim/_generated/__init__.py
icclim/_generated/_dcsc.py
icclim/_generated/_ecad.py
icclim/_generated/_generic.py
icclim/dcsc/__init__.py
icclim/dcsc/registry.py
icclim/ecad/__init__.py
icclim/ecad/binding.py
icclim/ecad/registry.py
icclim/generic/__init__.py
icclim/generic/registry.py
icclim/threshold/__init__.py
icclim/threshold/factory.py
icclim-7.0.4.dist-info/licenses/LICENSE
icclim-7.0.4.dist-info/WHEEL
icclim-7.0.4.dist-info/METADATA
icclim-7.0.4.dist-info/RECORD
