Metadata-Version: 2.4
Name: icclim
Version: 7.0.4
Summary: Python library for climate indices calculation.
Keywords: netcdf,climate,climate-indices,climate-indicators,xarray
Author-email: Christian Page <christian.page@cerfacs.fr>
Maintainer-email: Christian Page <christian.page@cerfacs.fr>, Abel Aoun <aoun.abel@gmail.com>
Requires-Python: >=3.10
Classifier: Programming Language :: Python
Classifier: Development Status :: 4 - Beta
Classifier: Intended Audience :: Science/Research
Classifier: License :: OSI Approved :: Apache Software License
Classifier: Natural Language :: English
Classifier: Operating System :: OS Independent
Classifier: Programming Language :: Python :: 3.10
Classifier: Topic :: Scientific/Engineering :: Atmospheric Science
License-File: LICENSE
Requires-Dist: numpy>=2.0.1
Requires-Dist: xarray>=2025.6.1
Requires-Dist: xclim>=0.58.1
Requires-Dist: cf_xarray>=0.10.6
Requires-Dist: cftime>=1.6.4
Requires-Dist: dask[array]>=2025.7.0
Requires-Dist: netCDF4>=1.7.2
Requires-Dist: psutil
Requires-Dist: zarr>=2.18.3
Requires-Dist: rechunker>=0.3, !=0.4
Requires-Dist: fsspec
Requires-Dist: pandas>=2.3.2
Requires-Dist: dateparser
Requires-Dist: pint>=0.24.4
Requires-Dist: jinja2
Requires-Dist: psutil
Requires-Dist: flit ; extra == "dev"
Requires-Dist: ruff ; extra == "dev"
Requires-Dist: pip ; extra == "dev"
Requires-Dist: pre-commit>=2.9 ; extra == "dev"
Requires-Dist: sphinx-autobuild ; extra == "dev"
Requires-Dist: docstring_parser ; extra == "dev"
Requires-Dist: sphinx>=8.1.3 ; extra == "doc"
Requires-Dist: sphinx_codeautolink ; extra == "doc"
Requires-Dist: sphinx_copybutton ; extra == "doc"
Requires-Dist: sphinx_lfs_content ; extra == "doc"
Requires-Dist: sphinx-autoapi ; extra == "doc"
Requires-Dist: pydata-sphinx-theme ; extra == "doc"
Requires-Dist: nbsphinx ; extra == "doc"
Requires-Dist: ipython ; extra == "doc"
Requires-Dist: pytest ; extra == "test"
Requires-Dist: pytest-cov ; extra == "test"
Project-URL: Documentation, https://icclim.readthedocs.io/en/latest/how_to/index.html
Project-URL: Source, https://github.com/cerfacs-globc/icclim/
Provides-Extra: dev
Provides-Extra: doc
Provides-Extra: test
